bizdurr/BusinessDuration.py
bizdurr/BusinessHours.py
bizdurr/BusinessHoursOverrides.py
bizdurr/__init__.py
bizdurr/utils.py
bizdurr-2.0.0.dist-info/WHEEL
bizdurr-2.0.0.dist-info/entry_points.txt
bizdurr-2.0.0.dist-info/METADATA
bizdurr-2.0.0.dist-info/RECORD
