Metadata-Version: 2.3
Name: bizdurr
Version: 2.0.0
Summary: A lightweight, flexible business duration calculator.
Keywords: business,duration,business duration,business hours,business schedule
Author: clrk
Author-email: clrk <patrick.cl@gmail.com>
Classifier: Development Status :: 5 - Production/Stable
Classifier: Intended Audience :: Developers
Classifier: License :: OSI Approved :: MIT License
Classifier: Programming Language :: Python :: 3
Classifier: Programming Language :: Python :: 3.10
Classifier: Programming Language :: Python :: 3.11
Classifier: Programming Language :: Python :: 3.12
Classifier: Programming Language :: Python :: 3.13
Classifier: Topic :: Software Development :: Libraries :: Python Modules
Requires-Python: >=3.10
Project-URL: Homepage, https://github.com/patclrk/bizdurr
Project-URL: Issues, https://github.com/patclrk/bizdurr/issues
Project-URL: Repository, https://github.com/patclrk/bizdurr
